CS230/Lab1/23b1016/23b1016_bcd_to_7_segment_behv.v
module bc_7 (x1,x2,x3,x4,A,B,C,D,E,F,G);

input x1,x2,x3,x4;
output A,B,C,D,E,F,G;

assign A = (!x1&!x2&x3) | (!x1&x2&x4) | (x1&!x2&!x3) | (!x2&!x3&!x4);
assign B = (!x1&!x2) | (!x1&x2&!x3&!x4) | (!x1&x2&x3&x4) | (x1&!x2&!x3);
assign C = (!x1&!x3) | (x1&!x2&!x3) | (!x1&x3&x4) | (!x1&x2&x3&!x4);
assign D = (!x2&!x3&!x4) | (!x1&!x2&x3) | (!x1&x2&!x3&x4) | (!x1&x2&x3&!x4);
assign E = (!x1&x3&!x4) | (!x2&!x3&!x4);
assign F = (!x1&!x2&!x3&!x4) | (!x1&x2&!x3) | (x1&!x2&x3) | (!x1&x2&x3&!x4);
assign G = (!x1&x2&!x3) | (!x1&!x2&x3) | (!x1&x3&x4) | (x1&!x2&!x3&!x4);

endmodule

CS230/Lab1/23b1016/23b1016_tb_bcd_to_7_segment_behv.v
module tb ();

wire A,B,C,D,E,F,G;
reg x1,x2,x3,x4;

bc_7 circuit (x1,x2,x3,x4,A,B,C,D,E,F,G);

initial begin
    x1 = 0;x2 = 0;x3=0;x4=1;
    $monitor("x1=%d,x2=%d,x3=%d,x4=%d,A=%d,B=%d,C=%d,D=%d,E=%d,F=%d,G=%d",x1,x2,x3,x4,A,B,C,D,E,F,G);

    $display("Harshil Solanki 23B1016");
    #2 x4=0;x3=1;
    #3 x4=1;
    #4 x2=1;x3=0;x4=0;
    #5 x4=1;
    #6 x3=1;x4=0;
    #7 x4=1;
    #8 x1=1;x2=0;x3=0;x4=0;
    #9 x4=1;
    #10 x1=0;x4=0;
    $finish;

end

initial begin
    $dumpfile("mydesign_tb.vcd");
    $dumpvars(0,circuit);
end

endmodule

CS230/Lab1/23b1016/mydesign_tb.vcd
$date
	Wed Aug  7 16:28:54 2024
$end
$version
	Icarus Verilog
$end
$timescale
	1s
$end
$scope module tb $end
$scope module circuit $end
$var wire 1 ! A $end
$var wire 1 " B $end
$var wire 1 # C $end
$var wire 1 $ D $end
$var wire 1 % E $end
$var wire 1 & F $end
$var wire 1 ' G $end
$var wire 1 ( x1 $end
$var wire 1 ) x2 $end
$var wire 1 * x3 $end
$var wire 1 + x4 $end
$upscope $end
$upscope $end
$enddefinitions $end
#0
$dumpvars
1+
0*
0)
0(
0'
0&
0%
0$
1#
1"
0!
$end
#2
1'
0#
1$
0&
1!
1%
1*
0+
#5
1#
0%
1+
#9
0!
0$
1&
0+
0*
1)
#14
1!
0"
1$
1+
#20
0!
0'
1%
0+
1*
#27
1!
1"
1'
1#
0$
0%
0&
1+
#35
1$
1%
0+
0*
0)
1(
#44
0$
0%
0'
1+
#54
1&
1$
1%
0'
0+
0(
